{
  "judge_id": 460,
  "result": "WA",
  "passed": 0,
  "total": 50,
  "score": 0,
  "test_details": [{"name":"1","status":"WA","time":0.00,"memory":5620},{"name":"10","status":"WA","time":0.00,"memory":5716},{"name":"11","status":"WA","time":0.00,"memory":5776},{"name":"12","status":"WA","time":0.00,"memory":5772},{"name":"13","status":"WA","time":0.00,"memory":5788},{"name":"14","status":"WA","time":0.00,"memory":5772},{"name":"15","status":"WA","time":0.00,"memory":5860},{"name":"16","status":"WA","time":0.00,"memory":5644},{"name":"17","status":"WA","time":0.00,"memory":5788},{"name":"18","status":"WA","time":0.00,"memory":5632},{"name":"19","status":"WA","time":0.00,"memory":5804},{"name":"2","status":"WA","time":0.00,"memory":5772},{"name":"20","status":"WA","time":0.00,"memory":7692},{"name":"21","status":"WA","time":0.18,"memory":116256},{"name":"22","status":"WA","time":0.23,"memory":135308},{"name":"23","status":"WA","time":0.15,"memory":116176},{"name":"24","status":"WA","time":0.14,"memory":107912},{"name":"25","status":"WA","time":0.02,"memory":19676},{"name":"26","status":"WA","time":0.09,"memory":69324},{"name":"27","status":"WA","time":0.21,"memory":135064},{"name":"28","status":"WA","time":0.10,"memory":80068},{"name":"29","status":"WA","time":0.15,"memory":116172},{"name":"3","status":"WA","time":0.00,"memory":5764},{"name":"30","status":"WA","time":0.07,"memory":48572},{"name":"31","status":"WA","time":0.07,"memory":55804},{"name":"32","status":"WA","time":0.15,"memory":100156},{"name":"33","status":"WA","time":0.21,"memory":157136},{"name":"34","status":"WA","time":0.01,"memory":16796},{"name":"35","status":"WA","time":0.19,"memory":145632},{"name":"36","status":"WA","time":0.13,"memory":92984},{"name":"37","status":"WA","time":0.15,"memory":116172},{"name":"38","status":"WA","time":0.02,"memory":17560},{"name":"39","status":"WA","time":0.21,"memory":135188},{"name":"4","status":"WA","time":0.00,"memory":5624},{"name":"40","status":"WA","time":0.07,"memory":45284},{"name":"41","status":"WA","time":0.12,"memory":80252},{"name":"42","status":"WA","time":0.01,"memory":11052},{"name":"43","status":"WA","time":0.19,"memory":145688},{"name":"44","status":"WA","time":0.11,"memory":86244},{"name":"45","status":"WA","time":0.10,"memory":64524},{"name":"46","status":"WA","time":0.16,"memory":116304},{"name":"47","status":"WA","time":0.18,"memory":135064},{"name":"48","status":"WA","time":0.19,"memory":135064},{"name":"49","status":"WA","time":0.21,"memory":157176},{"name":"5","status":"WA","time":0.00,"memory":5788},{"name":"50","status":"WA","time":0.14,"memory":107784},{"name":"6","status":"WA","time":0.00,"memory":5624},{"name":"7","status":"WA","time":0.00,"memory":5788},{"name":"8","status":"WA","time":0.00,"memory":5628},{"name":"9","status":"WA","time":0.00,"memory":5568}]
}
